{"v":"5.6.10","fr":60,"ip":0,"op":141,"w":1000,"h":1000,"nm":"heart burst","ddd":0,"assets":[],"layers":[{"ddd":0,"ind":1,"ty":4,"nm":"heart05","sr":1,"ks":{"o":{"a":1,"k":[{"i":{"x":[0.833],"y":[0.833]},"o":{"x":[0.167],"y":[0.167]},"t":71,"s":[2]},{"i":{"x":[0.833],"y":[0.833]},"o":{"x":[0.167],"y":[0.167]},"t":79.008,"s":[100]},{"i":{"x":[0.833],"y":[0.833]},"o":{"x":[0.167],"y":[0.167]},"t":125.055,"s":[100]},{"t":133.0625,"s":[2]}],"ix":11},"r":{"a":1,"k":[{"i":{"x":[0.833],"y":[0.833]},"o":{"x":[0.167],"y":[0.167]},"t":71,"s":[-29]},{"i":{"x":[0.833],"y":[0.833]},"o":{"x":[0.167],"y":[0.167]},"t":89.018,"s":[11]},{"i":{"x":[0.833],"y":[0.833]},"o":{"x":[0.167],"y":[0.167]},"t":109.037,"s":[-9]},{"t":133.0625,"s":[-30]}],"ix":10},"p":{"a":1,"k":[{"i":{"x":0.833,"y":0.833},"o":{"x":0.167,"y":0.167},"t":71,"s":[710.376,858.961,0],"to":[-35.333,-17,0],"ti":[4.376,78.961,0]},{"i":{"x":0.833,"y":0.833},"o":{"x":0.167,"y":0.167},"t":89,"s":[594.376,672.961,0],"to":[-4.376,-78.961,0],"ti":[2.376,90.961,0]},{"i":{"x":0.833,"y":0.833},"o":{"x":0.167,"y":0.167},"t":109,"s":[704.376,466.961,0],"to":[-2.376,-90.961,0],"ti":[25.667,20.333,0]},{"t":133.0625,"s":[610.376,284.961,0]}],"ix":2},"a":{"a":0,"k":[253.863,205.896,0],"ix":1},"s":{"a":0,"k":[25,25,100],"ix":6}},"ao":0,"shapes":[{"ty":"gr","it":[{"ind":0,"ty":"sh","ix":1,"ks":{"a":0,"k":{"i":[[52.81,-85.02],[0,0],[47.442,76.364],[-93.703,18.035],[-5.567,-22.487],[-101.09,-19.456]],"o":[[-51.665,83.16],[0,0],[-52.809,-85.019],[106.716,-20.542],[5.718,-21.877],[93.695,18.035]],"v":[[200.803,14.999],[0.391,205.646],[-200.805,10.699],[-145.413,-185.104],[0.557,-69.096],[145.41,-180.805]],"c":true},"ix":2},"nm":"Path 1","mn":"ADBE Vector Shape - Group","hd":false},{"ty":"fl","c":{"a":0,"k":[0.956862745098,0.435278709262,0.54525122549,1],"ix":4},"o":{"a":0,"k":100,"ix":5},"r":1,"bm":0,"nm":"Fill 1","mn":"ADBE Vector Graphic - Fill","hd":false},{"ty":"tr","p":{"a":0,"k":[253.863,205.896],"ix":2},"a":{"a":0,"k":[0,0],"ix":1},"s":{"a":0,"k":[100,100],"ix":3},"r":{"a":0,"k":0,"ix":6},"o":{"a":0,"k":100,"ix":7},"sk":{"a":0,"k":0,"ix":4},"sa":{"a":0,"k":0,"ix":5},"nm":"Transform"}],"nm":"Group 1","np":2,"cix":2,"bm":0,"ix":1,"mn":"ADBE Vector Group","hd":false}],"ip":71,"op":133,"st":71,"bm":0},{"ddd":0,"ind":2,"ty":4,"nm":"heart03","sr":1,"ks":{"o":{"a":1,"k":[{"i":{"x":[0.833],"y":[0.833]},"o":{"x":[0.167],"y":[0.167]},"t":32,"s":[2]},{"i":{"x":[0.833],"y":[0.833]},"o":{"x":[0.167],"y":[0.167]},"t":40.008,"s":[100]},{"i":{"x":[0.833],"y":[0.833]},"o":{"x":[0.167],"y":[0.167]},"t":86.055,"s":[100]},{"t":94.0625,"s":[2]}],"ix":11},"r":{"a":1,"k":[{"i":{"x":[0.833],"y":[0.833]},"o":{"x":[0.167],"y":[0.167]},"t":32,"s":[-29]},{"i":{"x":[0.833],"y":[0.833]},"o":{"x":[0.167],"y":[0.167]},"t":50.018,"s":[11]},{"i":{"x":[0.833],"y":[0.833]},"o":{"x":[0.167],"y":[0.167]},"t":70.037,"s":[-9]},{"t":94.0625,"s":[-30]}],"ix":10},"p":{"a":1,"k":[{"i":{"x":0.833,"y":0.833},"o":{"x":0.167,"y":0.167},"t":32,"s":[350.376,798.961,0],"to":[-35.333,-17,0],"ti":[4.376,78.961,0]},{"i":{"x":0.833,"y":0.833},"o":{"x":0.167,"y":0.167},"t":50.084,"s":[234.376,612.961,0],"to":[-4.376,-78.961,0],"ti":[2.376,90.961,0]},{"i":{"x":0.833,"y":0.833},"o":{"x":0.167,"y":0.167},"t":70,"s":[344.376,406.961,0],"to":[-2.376,-90.961,0],"ti":[25.667,20.333,0]},{"t":94.0625,"s":[250.376,224.961,0]}],"ix":2},"a":{"a":0,"k":[253.863,205.896,0],"ix":1},"s":{"a":0,"k":[25,25,100],"ix":6}},"ao":0,"shapes":[{"ty":"gr","it":[{"ind":0,"ty":"sh","ix":1,"ks":{"a":0,"k":{"i":[[52.81,-85.02],[0,0],[47.442,76.364],[-93.703,18.035],[-5.567,-22.487],[-101.09,-19.456]],"o":[[-51.665,83.16],[0,0],[-52.809,-85.019],[106.716,-20.542],[5.718,-21.877],[93.695,18.035]],"v":[[200.803,14.999],[0.391,205.646],[-200.805,10.699],[-145.413,-185.104],[0.557,-69.096],[145.41,-180.805]],"c":true},"ix":2},"nm":"Path 1","mn":"ADBE Vector Shape - Group","hd":false},{"ty":"fl","c":{"a":0,"k":[0.811764705882,0.111418682921,0.25908203125,1],"ix":4},"o":{"a":0,"k":100,"ix":5},"r":1,"bm":0,"nm":"Fill 1","mn":"ADBE Vector Graphic - Fill","hd":false},{"ty":"tr","p":{"a":0,"k":[253.863,205.896],"ix":2},"a":{"a":0,"k":[0,0],"ix":1},"s":{"a":0,"k":[100,100],"ix":3},"r":{"a":0,"k":0,"ix":6},"o":{"a":0,"k":100,"ix":7},"sk":{"a":0,"k":0,"ix":4},"sa":{"a":0,"k":0,"ix":5},"nm":"Transform"}],"nm":"Group 1","np":2,"cix":2,"bm":0,"ix":1,"mn":"ADBE Vector Group","hd":false}],"ip":32,"op":94,"st":32,"bm":0},{"ddd":0,"ind":3,"ty":4,"nm":"heart04","sr":1,"ks":{"o":{"a":1,"k":[{"i":{"x":[0.833],"y":[0.833]},"o":{"x":[0.167],"y":[0.167]},"t":54,"s":[2]},{"i":{"x":[0.833],"y":[0.833]},"o":{"x":[0.167],"y":[0.167]},"t":62.008,"s":[100]},{"i":{"x":[0.833],"y":[0.833]},"o":{"x":[0.167],"y":[0.167]},"t":108.055,"s":[100]},{"t":116.0625,"s":[2]}],"ix":11},"r":{"a":1,"k":[{"i":{"x":[0.833],"y":[0.833]},"o":{"x":[0.167],"y":[0.167]},"t":54,"s":[26]},{"i":{"x":[0.833],"y":[0.833]},"o":{"x":[0.167],"y":[0.167]},"t":72,"s":[11]},{"i":{"x":[0.833],"y":[0.833]},"o":{"x":[0.167],"y":[0.167]},"t":92,"s":[-37]},{"t":116,"s":[38]}],"ix":10},"p":{"a":1,"k":[{"i":{"x":0.833,"y":0.833},"o":{"x":0.167,"y":0.167},"t":54,"s":[350.376,708.961,0],"to":[15,-30,0],"ti":[5,59.833,0]},{"i":{"x":0.833,"y":0.833},"o":{"x":0.167,"y":0.167},"t":72,"s":[440.376,528.961,0],"to":[-5,-59.833,0],"ti":[-1,64.833,0]},{"i":{"x":0.833,"y":0.833},"o":{"x":0.167,"y":0.167},"t":92,"s":[320.376,349.961,0],"to":[1,-64.833,0],"ti":[-21,35,0]},{"t":116,"s":[446.376,139.961,0]}],"ix":2},"a":{"a":0,"k":[253.863,205.896,0],"ix":1},"s":{"a":0,"k":[34,34,100],"ix":6}},"ao":0,"shapes":[{"ty":"gr","it":[{"ind":0,"ty":"sh","ix":1,"ks":{"a":0,"k":{"i":[[52.81,-85.02],[0,0],[47.442,76.364],[-93.703,18.035],[-5.567,-22.487],[-101.09,-19.456]],"o":[[-51.665,83.16],[0,0],[-52.809,-85.019],[106.716,-20.542],[5.718,-21.877],[93.695,18.035]],"v":[[200.803,14.999],[0.391,205.646],[-200.805,10.699],[-145.413,-185.104],[0.557,-69.096],[145.41,-180.805]],"c":true},"ix":2},"nm":"Path 1","mn":"ADBE Vector Shape - Group","hd":false},{"ty":"fl","c":{"a":0,"k":[0.925490196078,0.228650515687,0.375574538287,1],"ix":4},"o":{"a":0,"k":100,"ix":5},"r":1,"bm":0,"nm":"Fill 1","mn":"ADBE Vector Graphic - Fill","hd":false},{"ty":"tr","p":{"a":0,"k":[253.863,205.896],"ix":2},"a":{"a":0,"k":[0,0],"ix":1},"s":{"a":0,"k":[100,100],"ix":3},"r":{"a":0,"k":0,"ix":6},"o":{"a":0,"k":100,"ix":7},"sk":{"a":0,"k":0,"ix":4},"sa":{"a":0,"k":0,"ix":5},"nm":"Transform"}],"nm":"Group 1","np":2,"cix":2,"bm":0,"ix":1,"mn":"ADBE Vector Group","hd":false}],"ip":54,"op":116,"st":54,"bm":0},{"ddd":0,"ind":4,"ty":4,"nm":"heart02","sr":1,"ks":{"o":{"a":1,"k":[{"i":{"x":[0.833],"y":[0.833]},"o":{"x":[0.167],"y":[0.167]},"t":19,"s":[2]},{"i":{"x":[0.833],"y":[0.833]},"o":{"x":[0.167],"y":[0.167]},"t":27.008,"s":[100]},{"i":{"x":[0.833],"y":[0.833]},"o":{"x":[0.167],"y":[0.167]},"t":73.055,"s":[100]},{"t":81.0625,"s":[2]}],"ix":11},"r":{"a":1,"k":[{"i":{"x":[0.833],"y":[0.833]},"o":{"x":[0.167],"y":[0.167]},"t":19,"s":[26]},{"i":{"x":[0.833],"y":[0.833]},"o":{"x":[0.167],"y":[0.167]},"t":37,"s":[11]},{"i":{"x":[0.833],"y":[0.833]},"o":{"x":[0.167],"y":[0.167]},"t":57,"s":[-37]},{"t":81,"s":[38]}],"ix":10},"p":{"a":1,"k":[{"i":{"x":0.833,"y":0.833},"o":{"x":0.167,"y":0.167},"t":19,"s":[500.376,798.961,0],"to":[15,-30,0],"ti":[5,59.833,0]},{"i":{"x":0.833,"y":0.833},"o":{"x":0.167,"y":0.167},"t":37,"s":[590.376,618.961,0],"to":[-5,-59.833,0],"ti":[-1,64.833,0]},{"i":{"x":0.833,"y":0.833},"o":{"x":0.167,"y":0.167},"t":57,"s":[470.376,439.961,0],"to":[1,-64.833,0],"ti":[-21,35,0]},{"t":81,"s":[596.376,229.961,0]}],"ix":2},"a":{"a":0,"k":[253.863,205.896,0],"ix":1},"s":{"a":0,"k":[34,34,100],"ix":6}},"ao":0,"shapes":[{"ty":"gr","it":[{"ind":0,"ty":"sh","ix":1,"ks":{"a":0,"k":{"i":[[52.81,-85.02],[0,0],[47.442,76.364],[-93.703,18.035],[-5.567,-22.487],[-101.09,-19.456]],"o":[[-51.665,83.16],[0,0],[-52.809,-85.019],[106.716,-20.542],[5.718,-21.877],[93.695,18.035]],"v":[[200.803,14.999],[0.391,205.646],[-200.805,10.699],[-145.413,-185.104],[0.557,-69.096],[145.41,-180.805]],"c":true},"ix":2},"nm":"Path 1","mn":"ADBE Vector Shape - Group","hd":false},{"ty":"fl","c":{"a":0,"k":[0.941176470588,0.531487857594,0.617867982154,1],"ix":4},"o":{"a":0,"k":100,"ix":5},"r":1,"bm":0,"nm":"Fill 1","mn":"ADBE Vector Graphic - Fill","hd":false},{"ty":"tr","p":{"a":0,"k":[253.863,205.896],"ix":2},"a":{"a":0,"k":[0,0],"ix":1},"s":{"a":0,"k":[100,100],"ix":3},"r":{"a":0,"k":0,"ix":6},"o":{"a":0,"k":100,"ix":7},"sk":{"a":0,"k":0,"ix":4},"sa":{"a":0,"k":0,"ix":5},"nm":"Transform"}],"nm":"Group 1","np":2,"cix":2,"bm":0,"ix":1,"mn":"ADBE Vector Group","hd":false}],"ip":19,"op":81,"st":19,"bm":0},{"ddd":0,"ind":5,"ty":4,"nm":"heart01","sr":1,"ks":{"o":{"a":1,"k":[{"i":{"x":[0.833],"y":[0.833]},"o":{"x":[0.167],"y":[0.167]},"t":0,"s":[2]},{"i":{"x":[0.833],"y":[0.833]},"o":{"x":[0.167],"y":[0.167]},"t":8.008,"s":[100]},{"i":{"x":[0.833],"y":[0.833]},"o":{"x":[0.167],"y":[0.167]},"t":54.055,"s":[100]},{"t":62.0625,"s":[2]}],"ix":11},"r":{"a":1,"k":[{"i":{"x":[0.833],"y":[0.833]},"o":{"x":[0.167],"y":[0.167]},"t":0,"s":[-29]},{"i":{"x":[0.833],"y":[0.833]},"o":{"x":[0.167],"y":[0.167]},"t":18.018,"s":[11]},{"i":{"x":[0.833],"y":[0.833]},"o":{"x":[0.167],"y":[0.167]},"t":38.037,"s":[-9]},{"t":62.0625,"s":[-30]}],"ix":10},"p":{"a":1,"k":[{"i":{"x":0.833,"y":0.833},"o":{"x":0.167,"y":0.167},"t":0,"s":[500.376,798.961,0],"to":[-35.333,-17,0],"ti":[4.376,78.961,0]},{"i":{"x":0.833,"y":0.833},"o":{"x":0.167,"y":0.167},"t":18.084,"s":[384.376,612.961,0],"to":[-4.376,-78.961,0],"ti":[2.376,90.961,0]},{"i":{"x":0.833,"y":0.833},"o":{"x":0.167,"y":0.167},"t":38,"s":[494.376,406.961,0],"to":[-2.376,-90.961,0],"ti":[25.667,20.333,0]},{"t":62.0625,"s":[400.376,224.961,0]}],"ix":2},"a":{"a":0,"k":[253.863,205.896,0],"ix":1},"s":{"a":0,"k":[34,34,100],"ix":6}},"ao":0,"shapes":[{"ty":"gr","it":[{"ind":0,"ty":"sh","ix":1,"ks":{"a":0,"k":{"i":[[52.81,-85.02],[0,0],[47.442,76.364],[-93.703,18.035],[-5.567,-22.487],[-101.09,-19.456]],"o":[[-51.665,83.16],[0,0],[-52.809,-85.019],[106.716,-20.542],[5.718,-21.877],[93.695,18.035]],"v":[[200.803,14.999],[0.391,205.646],[-200.805,10.699],[-145.413,-185.104],[0.557,-69.096],[145.41,-180.805]],"c":true},"ix":2},"nm":"Path 1","mn":"ADBE Vector Shape - Group","hd":false},{"ty":"fl","c":{"a":0,"k":[0.909803981407,0.258823529412,0.396078461292,1],"ix":4},"o":{"a":0,"k":100,"ix":5},"r":1,"bm":0,"nm":"Fill 1","mn":"ADBE Vector Graphic - Fill","hd":false},{"ty":"tr","p":{"a":0,"k":[253.863,205.896],"ix":2},"a":{"a":0,"k":[0,0],"ix":1},"s":{"a":0,"k":[100,100],"ix":3},"r":{"a":0,"k":0,"ix":6},"o":{"a":0,"k":100,"ix":7},"sk":{"a":0,"k":0,"ix":4},"sa":{"a":0,"k":0,"ix":5},"nm":"Transform"}],"nm":"Group 1","np":2,"cix":2,"bm":0,"ix":1,"mn":"ADBE Vector Group","hd":false}],"ip":0,"op":62,"st":0,"bm":0},{"ddd":0,"ind":6,"ty":1,"nm":"background","sr":1,"ks":{"o":{"a":0,"k":100,"ix":11},"r":{"a":0,"k":0,"ix":10},"p":{"a":0,"k":[500,500,0],"ix":2},"a":{"a":0,"k":[500,500,0],"ix":1},"s":{"a":0,"k":[100,100,100],"ix":6}},"ao":0,"sw":1000,"sh":1000,"sc":"#ffffff","ip":0,"op":141,"st":0,"bm":0}],"markers":[]}